flexivrdk/__init__.py
flexivrdk/flexivrdk.cp312-win_amd64.pyd
flexivrdk-1.7.0.dist-info/licenses/LICENSE
flexivrdk-1.7.0.dist-info/METADATA
flexivrdk-1.7.0.dist-info/WHEEL
flexivrdk-1.7.0.dist-info/top_level.txt
flexivrdk-1.7.0.dist-info/RECORD
